SystemMonitorAgent/__init__.py
SystemMonitorAgent/core.py
systemmonitoragent-0.1.1.dist-info/LICENSE
systemmonitoragent-0.1.1.dist-info/METADATA
systemmonitoragent-0.1.1.dist-info/WHEEL
systemmonitoragent-0.1.1.dist-info/top_level.txt
systemmonitoragent-0.1.1.dist-info/RECORD
