Metadata-Version: 2.1
Name: systemmonitoragent
Version: 0.1.1
Summary: Just to monitor your system
Classifier: Programming Language :: Python :: 3
Classifier: License :: OSI Approved :: MIT License
Classifier: Operating System :: OS Independent
Requires-Python: >=3.6
License-File: LICENSE
Requires-Dist: requests
